Workbook

Sheet Inventory_Ledger
A1: Date | B1: Opening Qty | C1: Purchases | D1: Transfers In | E1: Transfers Out | F1: Spoilage | G1: Theoretical Closing | H1: Physical Count | I1: Variance Qty | J1: Unit Cost (CP) | K1: Variance Value | L1: Variance % | M1: Control Flag
A2: 45876 | B2: 100 | C2: 0 | D2: 0 | E2: 5 | F2: 0 | G2: =B2+C2+D2-E2-F2 -> 95 | H2: 95 | I2: =H2-G2 -> 0 | J2: 85 | K2: =I2*J2 -> 0 | L2: =IF(G2=0,0,I2/G2) -> 0 | M2: =IF(ABS(L2)>0.03,"Investigate","OK") -> OK
A3: 45877 | B3: =G2 -> 95 | C3: 0 | D3: 0 | E3: 6 | F3: 0 | G3: =B3+C3+D3-E3-F3 -> 89 | H3: 89 | I3: =H3-G3 -> 0 | J3: 85 | K3: =I3*J3 -> 0 | L3: =IF(G3=0,0,I3/G3) -> 0 | M3: =IF(ABS(L3)>0.03,"Investigate","OK") -> OK
A4: 45878 | B4: =G3 -> 89 | C4: 0 | D4: 0 | E4: 4 | F4: 0 | G4: =B4+C4+D4-E4-F4 -> 85 | H4: 85 | I4: =H4-G4 -> 0 | J4: 85 | K4: =I4*J4 -> 0 | L4: =IF(G4=0,0,I4/G4) -> 0 | M4: =IF(ABS(L4)>0.03,"Investigate","OK") -> OK
A5: 45879 | B5: =G4 -> 85 | C5: 0 | D5: 0 | E5: 5 | F5: 1 | G5: =B5+C5+D5-E5-F5 -> 79 | H5: 79 | I5: =H5-G5 -> 0 | J5: 85 | K5: =I5*J5 -> 0 | L5: =IF(G5=0,0,I5/G5) -> 0 | M5: =IF(ABS(L5)>0.03,"Investigate","OK") -> OK
A6: 45880 | B6: =G5 -> 79 | C6: 50 | D6: 0 | E6: 7 | F6: 0 | G6: =B6+C6+D6-E6-F6 -> 122 | H6: 122 | I6: =H6-G6 -> 0 | J6: 85 | K6: =I6*J6 -> 0 | L6: =IF(G6=0,0,I6/G6) -> 0 | M6: =IF(ABS(L6)>0.03,"Investigate","OK") -> OK
A7: 45881 | B7: =G6 -> 122 | C7: 0 | D7: 0 | E7: 8 | F7: 0 | G7: =B7+C7+D7-E7-F7 -> 114 | H7: 114 | I7: =H7-G7 -> 0 | J7: 85 | K7: =I7*J7 -> 0 | L7: =IF(G7=0,0,I7/G7) -> 0 | M7: =IF(ABS(L7)>0.03,"Investigate","OK") -> OK
A8: 45882 | B8: =G7 -> 114 | C8: 0 | D8: 0 | E8: 5 | F8: 0 | G8: =B8+C8+D8-E8-F8 -> 109 | H8: 112 | I8: =H8-G8 -> 3 | J8: 85 | K8: =I8*J8 -> 255 | L8: =IF(G8=0,0,I8/G8) -> 0.027522936 | M8: =IF(ABS(L8)>0.03,"Investigate","OK") -> OK
A9: 45883 | B9: =G8 -> 109 | C9: 0 | D9: 0 | E9: 6 | F9: 0 | G9: =B9+C9+D9-E9-F9 -> 103 | H9: 103 | I9: =H9-G9 -> 0 | J9: 85 | K9: =I9*J9 -> 0 | L9: =IF(G9=0,0,I9/G9) -> 0 | M9: =IF(ABS(L9)>0.03,"Investigate","OK") -> OK
A10: 45884 | B10: =G9 -> 103 | C10: 0 | D10: 0 | E10: 8 | F10: 0 | G10: =B10+C10+D10-E10-F10 -> 95 | H10: 95 | I10: =H10-G10 -> 0 | J10: 85 | K10: =I10*J10 -> 0 | L10: =IF(G10=0,0,I10/G10) -> 0 | M10: =IF(ABS(L10)>0.03,"Investigate","OK") -> OK
A11: 45885 | B11: =G10 -> 95 | C11: 0 | D11: 0 | E11: 4 | F11: 0 | G11: =B11+C11+D11-E11-F11 -> 91 | H11: 91 | I11: =H11-G11 -> 0 | J11: 85 | K11: =I11*J11 -> 0 | L11: =IF(G11=0,0,I11/G11) -> 0 | M11: =IF(ABS(L11)>0.03,"Investigate","OK") -> OK
A12: 45886 | B12: =G11 -> 91 | C12: 0 | D12: 0 | E12: 3 | F12: 0 | G12: =B12+C12+D12-E12-F12 -> 88 | H12: 88 | I12: =H12-G12 -> 0 | J12: 85 | K12: =I12*J12 -> 0 | L12: =IF(G12=0,0,I12/G12) -> 0 | M12: =IF(ABS(L12)>0.03,"Investigate","OK") -> OK
A13: 45887 | B13: =G12 -> 88 | C13: 0 | D13: 0 | E13: 6 | F13: 1 | G13: =B13+C13+D13-E13-F13 -> 81 | H13: 79 | I13: =H13-G13 -> -2 | J13: 85 | K13: =I13*J13 -> -170 | L13: =IF(G13=0,0,I13/G13) -> -0.024691358 | M13: =IF(ABS(L13)>0.03,"Investigate","OK") -> OK
A14: 45888 | B14: =G13 -> 81 | C14: 0 | D14: 0 | E14: 5 | F14: 0 | G14: =B14+C14+D14-E14-F14 -> 76 | H14: 76 | I14: =H14-G14 -> 0 | J14: 85 | K14: =I14*J14 -> 0 | L14: =IF(G14=0,0,I14/G14) -> 0 | M14: =IF(ABS(L14)>0.03,"Investigate","OK") -> OK
... A30: 45904 | B30: =G29 -> 74 | C30: 0 | D30: 0 | E30: 8 | F30: 0 | G30: =B30+C30+D30-E30-F30 -> 66 | H30: 66 | I30: =H30-G30 -> 0 | J30: 85 | K30: =I30*J30 -> 0 | L30: =IF(G30=0,0,I30/G30) -> 0 | M30: =IF(ABS(L30)>0.03,"Investigate","OK") -> OK
E31: =SUM(E2:E30) -> 161 | F31: =SUM(F2:F30) -> 3 | I31: =I13+I8+I23 -> -3
A32: SUMMARY
A33: Total Purchases | B33: =SUM(C2:C31) -> 130
A34: Total Spoilage | B34: =SUM(F2:F31) -> 6
A35: Total Variance Value | B35: =SUM(K2:K31) -> -255
A36: Ending Inventory Value | B36: =G30*J30 -> 5610

Sheet COGS_Reconciliation
A1: Inventory Summary
A2: Opening Inventory Value | B2: =Inventory_Ledger!B2*Inventory_Ledger!J2 -> 8500
A3: Purchases Value | B3: =SUM(Inventory_Ledger!C2:C31)*Inventory_Ledger!J2 -> 11050 | D3: Assumptions
A4: Closing Inventory Value | B4: =Inventory_Ledger!G30*Inventory_Ledger!J2 -> 5610 | D4: Cost per Bottle (CP) | E4: 85
A5: COGS | B5: =B2+B3-B4 -> 13940 | D5: Bottles Sold | E5: 164 | F5: From E31 (Invetory_Ledger)
D6: Revenue per Bottle (SP) | E6: 380
A7: Revenue | D7: Discount % | E7: 0.08
A8: Total Beverage Revenue | B8: =E6*E5 -> 62320
A9: Discounts | B9: =B8*E7 -> 4985.6
A10: Net Revenue | B10: =B8-B9 -> 57334.4
A11: COGS | B11: =B5 -> 13940
A12: Gross Profit | B12: =B10-B5 -> 43394.4
A13: Gross Margin % | B13: =(B10-B5)/B10 -> 0.75686499
A14: Beverage Cost % | B14: =B5/B10 -> 0.24313501
A16: Budget Control
A17: Metric | B17: Budget | C17: Actual | D17: Variance | E17: Variance %
A18: COGS | B18: 13000 | C18: 13940 | D18: =C18-B18 -> 940 | E18: =D18/B18 -> 0.072307692

Sheet Event_Monitoring
A1: Date | B1: Event | C1: Expected | D1: Actual | E1: Variance | F1: Event COGS | G1: Event Revenue
A2: 45892 | B2: Wedding | C2: 6 | D2: 9 | E2: 3 | F2: =9*85 -> 765 | G2: =9*380 -> 3420
A3: 45899 | B3: Corporate | C3: 6 | D3: 9 | E3: 3 | F3: =9*85 -> 765 | G3: =9*380 -> 3420

Sheet Dashboard
A1: Core KPIs
A2: Total Revenue | B2: Net Revenue | C2: COGS
A3: =COGS_Reconciliation!B8 -> 62320 | B3: =COGS_Reconciliation!B10 -> 57334.4 | C3: =COGS_Reconciliation!B5 -> 13940
A4: Gross Margin % | B4: Beverage Cost %
A5: =COGS_Reconciliation!B13 -> 0.75686499 | B5: =COGS_Reconciliation!B14 -> 0.24313501
A6: Inventory Variance % | B6: Spoilage %
A7: =Inventory_Ledger!I31/Inventory_Ledger!E31 -> -0.01863354 | B7: =Inventory_Ledger!F31/Inventory_Ledger!E31 -> 0.01863354
A10: Status
A11: Metric | B11: Status
A12: Beverage Cost % | B12: =IF(COGS_Reconciliation!B14%<=0.25,"Within Target","Over Target") -> Within Target
A13: Inventory Variance | B13: =IF(ABS(A7)<=0.03,"Controlled","Investigate") -> Controlled
A14: Discount Level | B14: =IF(COGS_Reconciliation!E7<=0.1,"Acceptable","High Discount Risk") -> Acceptable
B46: Metric | C46: Value
B47: Net Revenue | C47: =COGS_Reconciliation!B10 -> 57334.4
B48: COGS | C48: =COGS_Reconciliation!B5 -> 13940
B50: Component | C50: Value
B51: COGS | C51: =C48 -> 13940
B52: Gross Profit | C52: =C47-C48 -> 43394.4

Sheet Control_Checklist
A1: Control Area | B1: Frequency | C1: Responsible | D1: Status | E1: Remarks
A2: Daily Inventory Posting | B2: Daily | C2: Cost Controller | D2: Completed | E2: No backlog
A3: Physical Count Verification | B3: Weekly | C3: Outlet Supervisor | D3: Completed | E3: Variance within 3%
A4: Variance >3% Investigation | B4: As Required | C4: Finance | D4: 1 Case | E4: Investigated on 28th
A5: Event Consumption Reconciliation | B5: Per Event | C5: Finance | D5: Completed | E5: Wedding over by 3 bottles
A6: Discount Review | B6: Monthly | C6: Finance | D6: Within Limit | E6: 8% vs 10% threshold
A7: Purchase Authorization Check | B7: Per Order | C7: Finance | D7: Approved | E7: All matched GRN
